yuercrank/__init__.py
yuercrank/main.py
yuercrank-0.0.2.dist-info/LICENSE.txt
yuercrank-0.0.2.dist-info/METADATA
yuercrank-0.0.2.dist-info/WHEEL
yuercrank-0.0.2.dist-info/top_level.txt
yuercrank-0.0.2.dist-info/RECORD
