Metadata-Version: 2.1
Name: yuercrank
Version: 0.0.2
Summary: Simple package
Author: The Urban Penguin
Author-email: crank3729@gmail.com
License-File: LICENSE.txt
Requires-Dist: telebot
